curl.py
cURL_light-7.64.0.1.data/scripts/curl.py
cURL_light-7.64.0.1.dist-info/LICENSE
cURL_light-7.64.0.1.dist-info/METADATA
cURL_light-7.64.0.1.dist-info/WHEEL
cURL_light-7.64.0.1.dist-info/top_level.txt
cURL_light-7.64.0.1.dist-info/zip-safe
cURL_light-7.64.0.1.dist-info/RECORD
