Metadata-Version: 2.1
Name: cURL-light
Version: 7.64.0.1
Summary: python library for transferring data specified with URL syntax using cURL
Home-page: https://github.com/Ksengine/cURL-light
Author: Kavindu Santhusa
Author-email: kavindusanthusa@gmail.com
License: MIT
Download-URL: https://pypi.python.org/pypi/cURL-light
Project-URL: Bug Tracker, https://github.com/Ksengine/cURL-light/issues
Keywords: python,library,transfer,data,URL,cURL
Platform: any
Classifier: Intended Audience :: Developers
Classifier: Development Status :: 5 - Production/Stable
Classifier: Operating System :: OS Independent
Classifier: License :: OSI Approved :: MIT License
Classifier: Operating System :: MacOS :: MacOS X
Classifier: Operating System :: Microsoft :: Windows
Classifier: Operating System :: POSIX
Classifier: Programming Language :: Python
Classifier: Programming Language :: Python :: 2.7
Classifier: Programming Language :: Python :: 3.4
Classifier: Programming Language :: Python :: 3.5
Classifier: Programming Language :: Python :: 3.6
Classifier: Programming Language :: Python :: 3.7
Classifier: Programming Language :: Python :: 3
Provides: cURL_light
